<?xml version="1.0" encoding="UTF-8"?>
<objects serializationModel="Studio.02.02.00">
	<object class="AudioFile" id="{b921f24b-f830-4097-a5e8-62d12a708ca1}">
		<property name="assetPath">
			<value>NarratorESP/5NarraESP.mp3</value>
		</property>
		<property name="frequencyInKHz">
			<value>44.0999985</value>
		</property>
		<property name="channelCount">
			<value>1</value>
		</property>
		<property name="length">
			<value>3.657142857142857</value>
		</property>
		<relationship name="masterAssetFolder">
			<destination>{bcaa4fde-f9c0-43f0-a606-36021ff0856e}</destination>
		</relationship>
	</object>
</objects>
